oathlink/__init__.py
oathlink/main/__init__.py
oathlink/main/oathlink.py
oathlink/services/__init__.py
oathlink/services/hello.py
oathlink/services/agent/__init__.py
oathlink/services/agent/account/__init__.py
oathlink/services/agent/account/create.py
oathlink/services/agent/account/link.py
oathlink/services/agent/account/unlink.py
oathlink/services/agent/ip/__init__.py
oathlink/services/agent/ip/add.py
oathlink/services/agent/ip/remove.py
oathlink/services/record/__init__.py
oathlink/services/record/archive.py
oathlink/services/record/cancel.py
oathlink/services/record/decrypt.py
oathlink/services/record/download.py
oathlink/services/record/upload.py
oathlink/services/report/__init__.py
oathlink/services/report/history.py
oathlink/services/report/outstanding.py
oathlink/services/report/record.py
oathlink/util/__init__.py
oathlink/util/crypto/Fernet.py
oathlink/util/crypto/__init__.py
oathlink/util/https/__init__.py
oathlink/util/https/https.py
oathlink-0.8.16.dist-info/LICENSE
oathlink-0.8.16.dist-info/METADATA
oathlink-0.8.16.dist-info/WHEEL
oathlink-0.8.16.dist-info/top_level.txt
oathlink-0.8.16.dist-info/RECORD
