Metadata-Version: 2.1
Name: oathlink
Version: 0.8.16
Summary: This repository holds the Oathlink user Python package (client source code).
Home-page: https://github.com/BurrusFinancialIntelligence/Oathlink-Client.git
Author: oathlink
Author-email: oathlink@bfi.lat
Project-URL: Bug Tracker, https://github.com/BurrusFinancialIntelligence/Oathlink-Client.git/issues
Classifier: Programming Language :: Python :: 3
Classifier: License :: Other/Proprietary License
Classifier: Operating System :: OS Independent
Requires-Python: >=3.7
License-File: LICENSE
Requires-Dist: certifi
Requires-Dist: cffi
Requires-Dist: charset-normalizer
Requires-Dist: cryptography
Requires-Dist: idna
Requires-Dist: pycparser
Requires-Dist: requests
Requires-Dist: urllib3
